{
    "sentences": [
        {
            "text": {
                "content": "this is a test text.",
                "beginOffset": 0
            }
        },
        {
            "text": {
                "content": "Thats great.",
                "beginOffset": 21
            }
        }
    ],
    "tokens": [
        {
            "text": {
                "content": "this",
                "beginOffset": 0
            },
            "partOfSpeech": {
                "tag": 5,
                "number": 1,
                "aspect": 0,
                "case": 0,
                "form": 0,
                "gender": 0,
                "mood": 0,
                "person": 0,
                "proper": 0,
                "reciprocity": 0,
                "tense": 0,
                "voice": 0
            },
            "dependencyEdge": {
                "headTokenIndex": 1,
                "label": 28
            },
            "lemma": "this"
        },
        {
            "text": {
                "content": "is",
                "beginOffset": 5
            },
            "partOfSpeech": {
                "tag": 11,
                "mood": 3,
                "number": 1,
                "person": 3,
                "tense": 4,
                "aspect": 0,
                "case": 0,
                "form": 0,
                "gender": 0,
                "proper": 0,
                "reciprocity": 0,
                "voice": 0
            },
            "dependencyEdge": {
                "headTokenIndex": 1,
                "label": 54
            },
            "lemma": "be"
        },
        {
            "text": {
                "content": "a",
                "beginOffset": 8
            },
            "partOfSpeech": {
                "tag": 5,
                "aspect": 0,
                "case": 0,
                "form": 0,
                "gender": 0,
                "mood": 0,
                "number": 0,
                "person": 0,
                "proper": 0,
                "reciprocity": 0,
                "tense": 0,
                "voice": 0
            },
            "dependencyEdge": {
                "headTokenIndex": 4,
                "label": 16
            },
            "lemma": "a"
        },
        {
            "text": {
                "content": "test",
                "beginOffset": 10
            },
            "partOfSpeech": {
                "tag": 6,
                "number": 1,
                "aspect": 0,
                "case": 0,
                "form": 0,
                "gender": 0,
                "mood": 0,
                "person": 0,
                "proper": 0,
                "reciprocity": 0,
                "tense": 0,
                "voice": 0
            },
            "dependencyEdge": {
                "headTokenIndex": 4,
                "label": 26
            },
            "lemma": "test"
        },
        {
            "text": {
                "content": "text",
                "beginOffset": 15
            },
            "partOfSpeech": {
                "tag": 6,
                "number": 1,
                "aspect": 0,
                "case": 0,
                "form": 0,
                "gender": 0,
                "mood": 0,
                "person": 0,
                "proper": 0,
                "reciprocity": 0,
                "tense": 0,
                "voice": 0
            },
            "dependencyEdge": {
                "headTokenIndex": 1,
                "label": 7
            },
            "lemma": "text"
        },
        {
            "text": {
                "content": ".",
                "beginOffset": 19
            },
            "partOfSpeech": {
                "tag": 10,
                "aspect": 0,
                "case": 0,
                "form": 0,
                "gender": 0,
                "mood": 0,
                "number": 0,
                "person": 0,
                "proper": 0,
                "reciprocity": 0,
                "tense": 0,
                "voice": 0
            },
            "dependencyEdge": {
                "headTokenIndex": 1,
                "label": 32
            },
            "lemma": "."
        },
        {
            "text": {
                "content": "Thats",
                "beginOffset": 21
            },
            "partOfSpeech": {
                "tag": 5,
                "aspect": 0,
                "case": 0,
                "form": 0,
                "gender": 0,
                "mood": 0,
                "number": 0,
                "person": 0,
                "proper": 0,
                "reciprocity": 0,
                "tense": 0,
                "voice": 0
            },
            "dependencyEdge": {
                "headTokenIndex": 7,
                "label": 4
            },
            "lemma": "Thats"
        },
        {
            "text": {
                "content": "great",
                "beginOffset": 27
            },
            "partOfSpeech": {
                "tag": 1,
                "aspect": 0,
                "case": 0,
                "form": 0,
                "gender": 0,
                "mood": 0,
                "number": 0,
                "person": 0,
                "proper": 0,
                "reciprocity": 0,
                "tense": 0,
                "voice": 0
            },
            "dependencyEdge": {
                "headTokenIndex": 7,
                "label": 54
            },
            "lemma": "great"
        },
        {
            "text": {
                "content": ".",
                "beginOffset": 32
            },
            "partOfSpeech": {
                "tag": 10,
                "aspect": 0,
                "case": 0,
                "form": 0,
                "gender": 0,
                "mood": 0,
                "number": 0,
                "person": 0,
                "proper": 0,
                "reciprocity": 0,
                "tense": 0,
                "voice": 0
            },
            "dependencyEdge": {
                "headTokenIndex": 7,
                "label": 32
            },
            "lemma": "."
        }
    ],
    "language": "en",
    "title": "some",
    "phoneticDict": {
        "this": "\u00f0\u02c8\u026as",
        "is": "\u02c8\u026az",
        "a": {
            "det": "\u02c8e\u026a",
            "noun": "\u02c8e\u026a"
        },
        "test": "t\u02c8\u025bst",
        "text": "t\u02c8\u025bkst",
        "great": "\u0261\u0279\u02c8e\u026at"
    },
    "text": "this is a test text. Thats great."
}